bicscan_mcp/__init__.py
bicscan_mcp/server.py
mseep_bicscan_mcp-0.1.1.dist-info/licenses/LICENSE
mseep_bicscan_mcp-0.1.1.dist-info/METADATA
mseep_bicscan_mcp-0.1.1.dist-info/WHEEL
mseep_bicscan_mcp-0.1.1.dist-info/entry_points.txt
mseep_bicscan_mcp-0.1.1.dist-info/top_level.txt
mseep_bicscan_mcp-0.1.1.dist-info/RECORD
