Metadata-Version: 2.4
Name: mseep-bicscan-mcp
Version: 0.1.1
Summary: BICScan MCP Server
Author-email: mseep <support@skydeck.ai>
Requires-Python: >=3.10
License-File: LICENSE
Requires-Dist: httpx>=0.28.1
Requires-Dist: mcp[cli]>=1.5.0
Requires-Dist: python-dotenv>=1.0.1
Dynamic: license-file
